xpctl/__init__.py
xpctl/cli.py
xpctl/clihelpers.py
xpctl/version.py
xpctl/backends/__init__.py
xpctl/backends/backend.py
xpctl/backends/core.py
xpctl/backends/mongo/__init__.py
xpctl/backends/mongo/store.py
xpctl/backends/sql/__init__.py
xpctl/backends/sql/store.py
xpctl/tests/__init__.py
xpctl/tests/test_xpctl.py
xpctl/util/__init__.py
xpctl/util/dump_restore.py
xpctl/xpserver/__init__.py
xpctl/xpserver/__main__.py
xpctl/xpserver/encoder.py
xpctl/xpserver/util.py
xpctl/xpserver/controllers/__init__.py
xpctl/xpserver/controllers/xpctl_controller.py
xpctl/xpserver/models/__init__.py
xpctl/xpserver/models/aggregate_result.py
xpctl/xpserver/models/aggregate_result_values.py
xpctl/xpserver/models/base_model_.py
xpctl/xpserver/models/experiment.py
xpctl/xpserver/models/experiment_aggregate.py
xpctl/xpserver/models/response.py
xpctl/xpserver/models/result.py
xpctl/xpserver/models/task_summary.py
xpctl/xpserver/test/__init__.py
xpctl/xpserver/test/test_xpctl_controller.py
mead_xpctl-1.2.3.dist-info/LICENSE
mead_xpctl-1.2.3.dist-info/METADATA
mead_xpctl-1.2.3.dist-info/NOTICE
mead_xpctl-1.2.3.dist-info/WHEEL
mead_xpctl-1.2.3.dist-info/entry_points.txt
mead_xpctl-1.2.3.dist-info/top_level.txt
mead_xpctl-1.2.3.dist-info/RECORD
