Metadata-Version: 2.1
Name: mead-xpctl
Version: 1.2.3
Summary: Experiment Control and Tracking
Home-page: https://www.github.com/mead-ml/xpctl
Author: mead-ml
Author-email: mead.baseline@gmail.com
License: Apache 2.0
Keywords: experiment control,tracking
Platform: UNKNOWN
Classifier: Topic :: Scientific/Engineering :: Artificial Intelligence
Classifier: Development Status :: 2 - Pre-Alpha
Classifier: License :: OSI Approved :: Apache Software License
Classifier: Programming Language :: Python :: 3.6
Classifier: Operating System :: OS Independent
Classifier: Natural Language :: English
Classifier: Intended Audience :: Developers
Classifier: Programming Language :: Python :: 2.7
Classifier: Environment :: Console
Classifier: Intended Audience :: Science/Research
Classifier: Programming Language :: Python :: 3.5
License-File: ./LICENSE
License-File: ./NOTICE
Requires-Dist: click
Requires-Dist: click-shell
Requires-Dist: pandas
Requires-Dist: xlsxwriter
Requires-Dist: jsondiff
Requires-Dist: pyyaml
Requires-Dist: certifi (>=14.05.14)
Requires-Dist: six (>=1.10)
Requires-Dist: python-dateutil (>=2.5.3)
Requires-Dist: setuptools (>=21.0.0)
Requires-Dist: urllib3 (>=1.15.1)
Requires-Dist: mead-xpctl-client (==1.2.3)
Provides-Extra: mongo
Requires-Dist: pymongo ; extra == 'mongo'
Provides-Extra: sql
Requires-Dist: sqlalchemy ; extra == 'sql'
Requires-Dist: psycopg2 ; extra == 'sql'
Provides-Extra: test
